phototrie/__init__.py
phototrie/batchrename.py
phototrie/datename.py
phototrie/phototrie.py
phototrie-0.1.0.dist-info/LICENCE
phototrie-0.1.0.dist-info/METADATA
phototrie-0.1.0.dist-info/WHEEL
phototrie-0.1.0.dist-info/entry_points.txt
phototrie-0.1.0.dist-info/top_level.txt
phototrie-0.1.0.dist-info/RECORD
