Metadata-Version: 2.1
Name: phototrie
Version: 0.1.0
Summary: Tools for sorting photos
Home-page: https://bics.ga/reivilibre/phototrie
Author: Olivier 'reivilibre'
Author-email: reivi@librepush.net
License: UNKNOWN
Platform: UNKNOWN
Classifier: Programming Language :: Python
Classifier: Programming Language :: Python :: 3
Requires-Python: >=3.7.0
Requires-Dist: ExifRead
Requires-Dist: Pillow
